sprice/__init__.py
sprice/core.py
sprice/data/sprice_data_1.h5
sprice/data/sprice_data_2.h5
sprice-0.1.1.dist-info/METADATA
sprice-0.1.1.dist-info/WHEEL
sprice-0.1.1.dist-info/top_level.txt
sprice-0.1.1.dist-info/RECORD
