Metadata-Version: 2.1
Name: sprice
Version: 0.1.1
Summary: Consumer price data package for Saudi Arabia
Home-page: https://github.com/amjad-alt/sprice
Author: Amjad Altuwayjiri
Author-email: amjadibrahim1994@gmail.com
License: UNKNOWN
Platform: UNKNOWN
Requires-Dist: pandas
Requires-Dist: h5py
